gzhlaker/__init__.py
gzhlaker/util_gemini.py
gzhlaker/util_openai.py
gzhlaker/util_oss.py
gzhlaker-0.0.6.dist-info/METADATA
gzhlaker-0.0.6.dist-info/WHEEL
gzhlaker-0.0.6.dist-info/top_level.txt
gzhlaker-0.0.6.dist-info/RECORD
