Metadata-Version: 2.1
Name: gzhlaker
Version: 0.0.6
Summary: Gzhlaker's lib
Author-email: "zihang.guo" <15047271937@163.com>
Project-URL: Homepage, https://github.com/guozihang/gzhlaker_pylib
Project-URL: Issues, https://github.com/guozihang/gzhlaker_pylib/issues
Classifier: Development Status :: 3 - Alpha
Classifier: Intended Audience :: Developers
Classifier: Programming Language :: Python :: 3 :: Only
Classifier: Operating System :: OS Independent
